groo/__init__.py
groo/groo.py
groo/groo_test.py
groo/test_script.py
groo_ozika-0.1.1.dist-info/LICENSE
groo_ozika-0.1.1.dist-info/METADATA
groo_ozika-0.1.1.dist-info/WHEEL
groo_ozika-0.1.1.dist-info/top_level.txt
groo_ozika-0.1.1.dist-info/RECORD
