Metadata-Version: 2.1
Name: groo-ozika
Version: 0.1.1
Summary: Get root directory based on file name
Home-page: https://github.com/ozika/groo
Author: Ondrej Zika
Author-email: ondrej.zika@protonmail.com
Project-URL: Bug Tracker, https://github.com/ozika/groo/issues
Classifier: Programming Language :: Python :: 3
Classifier: License :: OSI Approved :: MIT License
Classifier: Operating System :: OS Independent
Requires-Python: >=3.6
License-File: LICENSE
